structlog_throttling/__init__.py
structlog_throttling/processors.py
structlog_throttling/throttlers.py
structlog_throttling-1.4.0.dist-info/WHEEL
structlog_throttling-1.4.0.dist-info/METADATA
structlog_throttling-1.4.0.dist-info/RECORD
