Metadata-Version: 2.4
Name: structlog-throttling
Version: 1.4.0
Summary: Log throttling utilities for structlog.
Keywords: structlog,throttling,throttle
License-Expression: MIT OR Apache-2.0
Classifier: Development Status :: 5 - Production/Stable
Classifier: License :: OSI Approved :: Apache Software License
Classifier: License :: OSI Approved :: MIT License
Classifier: Programming Language :: Python :: 3.9
Classifier: Programming Language :: Python :: 3.10
Classifier: Programming Language :: Python :: 3.11
Classifier: Programming Language :: Python :: 3.12
Classifier: Programming Language :: Python :: 3.13
Classifier: Programming Language :: Python :: 3.14
Classifier: Topic :: System :: Logging
Classifier: Typing :: Typed
Requires-Dist: structlog>=25.5.0
Requires-Python: >=3.9
Project-URL: Codeberg, https://codeberg.org/tomasfarias/structlog-throttling
